odoo/addons/fieldservice_sale_stock_product_tags/README.rst
odoo/addons/fieldservice_sale_stock_product_tags/__init__.py
odoo/addons/fieldservice_sale_stock_product_tags/__manifest__.py
odoo/addons/fieldservice_sale_stock_product_tags/i18n/ca.po
odoo/addons/fieldservice_sale_stock_product_tags/i18n/es.po
odoo/addons/fieldservice_sale_stock_product_tags/i18n/fieldservice_sale_stock_product_tags.pot
odoo/addons/fieldservice_sale_stock_product_tags/models/__init__.py
odoo/addons/fieldservice_sale_stock_product_tags/models/fsm_order.py
odoo/addons/fieldservice_sale_stock_product_tags/models/product_template.py
odoo/addons/fieldservice_sale_stock_product_tags/models/sale_order.py
odoo/addons/fieldservice_sale_stock_product_tags/readme/CONTRIBUTORS.rst
odoo/addons/fieldservice_sale_stock_product_tags/readme/DESCRIPTION.rst
odoo/addons/fieldservice_sale_stock_product_tags/readme/USAGE.rst
odoo/addons/fieldservice_sale_stock_product_tags/static/description/icon.png
odoo/addons/fieldservice_sale_stock_product_tags/static/description/index.html
odoo/addons/fieldservice_sale_stock_product_tags/tests/__init__.py
odoo/addons/fieldservice_sale_stock_product_tags/tests/test_fsm_order_tags.py
odoo_addon_fieldservice_sale_stock_product_tags-15.0.1.0.0.2.dist-info/METADATA
odoo_addon_fieldservice_sale_stock_product_tags-15.0.1.0.0.2.dist-info/WHEEL
odoo_addon_fieldservice_sale_stock_product_tags-15.0.1.0.0.2.dist-info/top_level.txt
odoo_addon_fieldservice_sale_stock_product_tags-15.0.1.0.0.2.dist-info/RECORD
